doovpy/__init__.py
doovpy/peegchat.py
doovpy-0.2.0.dist-info/LICENSE
doovpy-0.2.0.dist-info/METADATA
doovpy-0.2.0.dist-info/WHEEL
doovpy-0.2.0.dist-info/top_level.txt
doovpy-0.2.0.dist-info/RECORD
