Metadata-Version: 2.1
Name: doovpy
Version: 0.2.0
Summary: A python package for a guys doov
Author: spogtrop
Author-email: spogtrop@gmail.com
Classifier: Programming Language :: Python :: 3
Classifier: License :: OSI Approved :: MIT License
Classifier: Operating System :: OS Independent
Requires-Python: >=3.6
License-File: LICENSE
